pyrogrambuildingutils/templates/__init__.py
pyrogrambuildingutils/templates/botClass.py
pyrogrambuildingutils/templates/envtemplate.py
pyrogrambuildingutils/utils/__init__.py
pyrogrambuildingutils/utils/pyrogram.py
pyrogrambuildingutils/utils/treeBuilder.py
pyrogrambuildingutils/utils/utils.py
pyrogrambuildingutils-0.0.8.dist-info/entry_points.txt
pyrogrambuildingutils-0.0.8.dist-info/METADATA
pyrogrambuildingutils-0.0.8.dist-info/WHEEL
pyrogrambuildingutils-0.0.8.dist-info/RECORD
